[{"alias":"rinkimekari","name":"micah","main_contact":"discord","other_contacts":null,"uses":["rust","casual linux","bass","music"],"skill":4,"social":3,"source":"discord"},{"alias":"ctfcryptic","name":"nick stepan","main_contact":"irl","other_contacts":["text","discord"],"uses":["windows user","patience tester","technically creative","hardware recs","mechining knowledge"],"skill":5,"social":5,"source":"interlake"},{"alias":"natalia","name":"natalie","main_contact":"text/call","other_contacts":["discord","school emaio","teams"],"uses":["art","animation","\"normal\""],"skill":0,"social":5,"source":"interlake"},{"alias":"caden","name":null,"main_contact":"irl","other_contacts":["teams","email"],"uses":["history knowledge","linguistics","hypothetical societal conversations"],"skill":0,"social":4,"source":"interlake"},{"alias":"marie","name":null,"main_contact":"irl","other_contacts":["text","call"],"uses":["book recommendations","fun hypothetical conversations","medical info (eventually)","writing"],"skill":3,"social":4,"source":"irl (elementary)"}]
